compute_horde_core/__init__.py
compute_horde_core/certificate.py
compute_horde_core/executor_class.py
compute_horde_core/signature.py
compute_horde_core/streaming.py
compute_horde_core/output_upload/__init__.py
compute_horde_core/output_upload/__main__.py
compute_horde_core/output_upload/_models.py
compute_horde_core/output_upload/_uploader.py
compute_horde_core/volume/__init__.py
compute_horde_core/volume/__main__.py
compute_horde_core/volume/_downloader.py
compute_horde_core/volume/_models.py
compute_horde_sdk/__init__.py
compute_horde_sdk/py.typed
compute_horde_sdk/_internal/__init__.py
compute_horde_sdk/_internal/exceptions.py
compute_horde_sdk/_internal/models.py
compute_horde_sdk/_internal/sdk.py
compute_horde_sdk/_internal/fallback/__init__.py
compute_horde_sdk/_internal/fallback/client.py
compute_horde_sdk/_internal/fallback/exceptions.py
compute_horde_sdk/_internal/fallback/job.py
compute_horde_sdk/_internal/fallback/utils.py
compute_horde_sdk/_internal/fallback/adaptors/__init__.py
compute_horde_sdk/_internal/fallback/adaptors/sky.py
compute_horde_sdk/_internal/fallback/adaptors/utils.py
compute_horde_sdk/v1/__init__.py
compute_horde_sdk/v1/fallback/__init__.py
compute_horde_sdk-0.0.18.dist-info/licenses/LICENSE
compute_horde_sdk-0.0.18.dist-info/METADATA
compute_horde_sdk-0.0.18.dist-info/WHEEL
compute_horde_sdk-0.0.18.dist-info/top_level.txt
compute_horde_sdk-0.0.18.dist-info/RECORD
