Metadata-Version: 2.4
Name: compute-horde-sdk
Version: 0.0.18
Author-email: Reef Technologies <opensource@reef.pl>
License: MIT
Project-URL: Source, https://github.com/backend-developers-ltd/compute-horde-sdk
Project-URL: Issue Tracker, https://github.com/backend-developers-ltd/compute-horde-sdk/issues
Classifier: Intended Audience :: Developers
Classifier: Topic :: Software Development :: Libraries
Classifier: License :: OSI Approved :: MIT License
Classifier: Programming Language :: Python :: 3
Classifier: Programming Language :: Python :: 3.10
Classifier: Programming Language :: Python :: 3.11
Classifier: Programming Language :: Python :: 3.12
Requires-Python: <3.13,>=3.10
License-File: LICENSE
Requires-Dist: asgiref<4,>=3.8.0
Requires-Dist: pydantic<3,>=2.3
Requires-Dist: httpx>=0.26.0
Requires-Dist: cryptography>=42.0.8
Requires-Dist: aiohttp>=3.12.0
Requires-Dist: bittensor-wallet~=4.0
Requires-Dist: tenacity<10.0.0,>=9.0.0
Requires-Dist: huggingface-hub[hf_transfer]>=0.26.1
Requires-Dist: async-timeout<5.0,>=4.0; python_version < "3.11"
Requires-Dist: backports.strenum; python_version < "3.11"
Provides-Extra: fallback
Requires-Dist: build; extra == "fallback"
Requires-Dist: wheel; extra == "fallback"
Requires-Dist: setuptools; extra == "fallback"
Requires-Dist: skypilot[runpod]<0.9.0,>=0.8.1; extra == "fallback"
Requires-Dist: gpustat<1.1; extra == "fallback"
Dynamic: license-file
